fix/__init__.py
fix/_version.py
fix/decorators.py
fix/util.py
fix-1.0.3.dist-info/DESCRIPTION.rst
fix-1.0.3.dist-info/METADATA
fix-1.0.3.dist-info/RECORD
fix-1.0.3.dist-info/WHEEL
fix-1.0.3.dist-info/metadata.json
fix-1.0.3.dist-info/top_level.txt
